jqai/__init__.py
jqai-0.1.5.dist-info/WHEEL
jqai-0.1.5.dist-info/entry_points.txt
jqai-0.1.5.dist-info/METADATA
jqai-0.1.5.dist-info/RECORD
