Metadata-Version: 2.3
Name: jqai
Version: 0.1.5
Summary: Generate and execute jq programs using LLMs
Author: Mason Hall
Author-email: Mason Hall <masonhall@gmail.com>
Requires-Dist: openai>=1.60.0
Requires-Dist: typer>=0.15.1
Requires-Python: >=3.12
